jellyfin_alexa_skill/__init__.py
jellyfin_alexa_skill/config.py
jellyfin_alexa_skill/main.py
jellyfin_alexa_skill/alexa/__init__.py
jellyfin_alexa_skill/alexa/util.py
jellyfin_alexa_skill/alexa/handler/__init__.py
jellyfin_alexa_skill/alexa/handler/base.py
jellyfin_alexa_skill/alexa/handler/channel.py
jellyfin_alexa_skill/alexa/handler/control.py
jellyfin_alexa_skill/alexa/handler/error.py
jellyfin_alexa_skill/alexa/handler/event.py
jellyfin_alexa_skill/alexa/handler/fallback.py
jellyfin_alexa_skill/alexa/handler/favorite.py
jellyfin_alexa_skill/alexa/handler/help.py
jellyfin_alexa_skill/alexa/handler/info.py
jellyfin_alexa_skill/alexa/handler/interface.py
jellyfin_alexa_skill/alexa/handler/launch.py
jellyfin_alexa_skill/alexa/handler/playlist.py
jellyfin_alexa_skill/alexa/handler/yesno.py
jellyfin_alexa_skill/alexa/setup/__init__.py
jellyfin_alexa_skill/alexa/setup/interaction/__init__.py
jellyfin_alexa_skill/alexa/setup/interaction/interaction_model_de_DE.json
jellyfin_alexa_skill/alexa/setup/interaction/interaction_model_en_US.json
jellyfin_alexa_skill/alexa/setup/interaction/model.py
jellyfin_alexa_skill/alexa/setup/manifest/__init__.py
jellyfin_alexa_skill/alexa/setup/manifest/manifest.json
jellyfin_alexa_skill/alexa/setup/manifest/manifest.py
jellyfin_alexa_skill/alexa/web/__init__.py
jellyfin_alexa_skill/alexa/web/skill.py
jellyfin_alexa_skill/database/__init__.py
jellyfin_alexa_skill/database/db.py
jellyfin_alexa_skill/database/model/__init__.py
jellyfin_alexa_skill/database/model/base.py
jellyfin_alexa_skill/database/model/playback.py
jellyfin_alexa_skill/database/model/user.py
jellyfin_alexa_skill/jellyfin/__init__.py
jellyfin_alexa_skill/jellyfin/api/__init__.py
jellyfin_alexa_skill/jellyfin/api/client.py
jellyfin_alexa_skill/jellyfin/web/__init__.py
jellyfin_alexa_skill/jellyfin/web/login.py
jellyfin_alexa_skill/jellyfin/web/templates/login.html
jellyfin_alexa_skill/locales/de/LC_MESSAGES/skill.mo
jellyfin_alexa_skill/locales/de/LC_MESSAGES/skill.po
jellyfin_alexa_skill-0.3.1.dist-info/LICENSE
jellyfin_alexa_skill-0.3.1.dist-info/METADATA
jellyfin_alexa_skill-0.3.1.dist-info/WHEEL
jellyfin_alexa_skill-0.3.1.dist-info/entry_points.txt
jellyfin_alexa_skill-0.3.1.dist-info/top_level.txt
jellyfin_alexa_skill-0.3.1.dist-info/RECORD
