Metadata-Version: 2.1
Name: jellyfin-alexa-skill
Version: 0.3.1
Summary: Selfhosted Alexa media player skill for Jellyfin
Home-page: https://github.com/infinityofspace/jellyfin_alexa_skill
Author: infinityofspace
License: MIT
Platform: UNKNOWN
Classifier: Development Status :: 3 - Alpha
Classifier: Programming Language :: Python :: 3
Classifier: Programming Language :: Python :: 3.6
Classifier: Programming Language :: Python :: 3.7
Classifier: Programming Language :: Python :: 3.8
Classifier: Programming Language :: Python :: 3.9
Classifier: Programming Language :: Python :: 3.10
Classifier: License :: OSI Approved :: GNU General Public License v3 (GPLv3)
Classifier: Topic :: Utilities
Classifier: Topic :: Multimedia :: Sound/Audio
Classifier: Topic :: Multimedia :: Video
Requires-Python: >=3.6
License-File: LICENSE
Requires-Dist: flask-ask-sdk (~=1.0.0)
Requires-Dist: pyngrok (~=5.1.0)
Requires-Dist: ask-smapi-sdk (~=1.0.0)
Requires-Dist: ask-smapi-model (~=1.13.1)
Requires-Dist: peewee (~=3.14.4)
Requires-Dist: gunicorn (~=20.1.0)
Requires-Dist: Flask-WTF (~=0.15.1)
